instant/__init__.py
instant/admin.py
instant/apps.py
instant/conf.py
instant/init.py
instant/models.py
instant/producers.py
instant/token.py
instant/urls.py
instant/views.py
instant/management/__init__.py
instant/management/__pycache__/__init__.cpython-310.pyc
instant/management/commands/__init__.py
instant/management/commands/installws.py
instant/management/commands/runws.py
instant/management/commands/__pycache__/__init__.cpython-310.pyc
instant/migrations/0001_initial.py
instant/migrations/0002_alter_channel_level.py
instant/migrations/__init__.py
instant/migrations/__pycache__/0001_initial.cpython-310.pyc
instant/migrations/__pycache__/0002_alter_channel_level.cpython-310.pyc
instant/migrations/__pycache__/__init__.cpython-310.pyc
instant/static/instant/index.min.js
instant/tests/__init__.py
instant/tests/base.py
instant/tests/runtests.py
instant/tests/test_conf.py
instant/tests/test_model.py
instant/tests/test_producers.py
instant/tests/test_token.py
instant/tests/test_utils.py
instant/tests/test_views.py
instant/tests/urls.py
django_instant-4.2.0.dist-info/LICENSE
django_instant-4.2.0.dist-info/METADATA
django_instant-4.2.0.dist-info/WHEEL
django_instant-4.2.0.dist-info/top_level.txt
django_instant-4.2.0.dist-info/RECORD
