Metadata-Version: 2.1
Name: django-instant
Version: 4.2.0
Summary: Websockets for Django with Centrifugo 
Home-page: https://github.com/synw/django-instant
Download-URL: https://github.com/synw/django-instant/releases/tag/4.2.0
Author: synw
Author-email: synwe@yahoo.com
Keywords: django,websockets,centrifugo
Classifier: Development Status :: 4 - Beta
Classifier: Framework :: Django :: 4.0
Classifier: Intended Audience :: Developers
Classifier: License :: OSI Approved :: MIT License
Classifier: Programming Language :: Python :: 3.8
License-File: LICENSE
